{
  "url": "https://api.github.com/repos/facebook/react/issues/5070",
  "repository_url": "https://api.github.com/repos/facebook/react",
  "labels_url": "https://api.github.com/repos/facebook/react/issues/5070/labels{/name}",
  "comments_url": "https://api.github.com/repos/facebook/react/issues/5070/comments",
  "events_url": "https://api.github.com/repos/facebook/react/issues/5070/events",
  "html_url": "https://github.com/facebook/react/issues/5070",
  "id": 110239628,
  "node_id": "MDU6SXNzdWUxMTAyMzk2Mjg=",
  "number": 5070,
  "title": "Order is not guaranteed in React.createFragment",
  "user": {
    "login": "idibidiart",
    "id": 1288823,
    "node_id": "MDQ6VXNlcjEyODg4MjM=",
    "avatar_url": "https://avatars3.githubusercontent.com/u/1288823?v=4",
    "gravatar_id": "",
    "url": "https://api.github.com/users/idibidiart",
    "html_url": "https://github.com/idibidiart",
    "followers_url": "https://api.github.com/users/idibidiart/followers",
    "following_url": "https://api.github.com/users/idibidiart/following{/other_user}",
    "gists_url": "https://api.github.com/users/idibidiart/gists{/gist_id}",
    "starred_url": "https://api.github.com/users/idibidiart/starred{/owner}{/repo}",
    "subscriptions_url": "https://api.github.com/users/idibidiart/subscriptions",
    "organizations_url": "https://api.github.com/users/idibidiart/orgs",
    "repos_url": "https://api.github.com/users/idibidiart/repos",
    "events_url": "https://api.github.com/users/idibidiart/events{/privacy}",
    "received_events_url": "https://api.github.com/users/idibidiart/received_events",
    "type": "User",
    "site_admin": false
  },
  "labels": [

  ],
  "state": "closed",
  "locked": false,
  "assignee": null,
  "assignees": [

  ],
  "milestone": null,
  "comments": 2,
  "created_at": "2015-10-07T14:36:59Z",
  "updated_at": "2015-10-07T14:56:39Z",
  "closed_at": "2015-10-07T14:56:39Z",
  "author_association": "NONE",
  "body": "According to the React docs [1] there seems to be an assumption that maps in Javascript guarantee the order of the keys which AFAIK is not true. See this Stackoverflow question [2]\n\n``` javascript\nif (this.props.swapped) {\n  children = React.addons.createFragment({\n    right: this.props.rightChildren,\n    left: this.props.leftChildren\n  });\n} else {\n  children = React.addons.createFragment({\n    left: this.props.leftChildren,\n    right: this.props.rightChildren\n  });\n}\n```\n\n[1] https://facebook.github.io/react/docs/create-fragment.html\n[2] http://stackoverflow.com/questions/5525795/does-javascript-guarantee-object-property-order\n\nCould this lead to cross-browser issues with CreateFragment?\n",
  "closed_by": {
    "login": "idibidiart",
    "id": 1288823,
    "node_id": "MDQ6VXNlcjEyODg4MjM=",
    "avatar_url": "https://avatars3.githubusercontent.com/u/1288823?v=4",
    "gravatar_id": "",
    "url": "https://api.github.com/users/idibidiart",
    "html_url": "https://github.com/idibidiart",
    "followers_url": "https://api.github.com/users/idibidiart/followers",
    "following_url": "https://api.github.com/users/idibidiart/following{/other_user}",
    "gists_url": "https://api.github.com/users/idibidiart/gists{/gist_id}",
    "starred_url": "https://api.github.com/users/idibidiart/starred{/owner}{/repo}",
    "subscriptions_url": "https://api.github.com/users/idibidiart/subscriptions",
    "organizations_url": "https://api.github.com/users/idibidiart/orgs",
    "repos_url": "https://api.github.com/users/idibidiart/repos",
    "events_url": "https://api.github.com/users/idibidiart/events{/privacy}",
    "received_events_url": "https://api.github.com/users/idibidiart/received_events",
    "type": "User",
    "site_admin": false
  }
}
