{
  "url": "https://api.github.com/repos/facebook/react/issues/5920",
  "repository_url": "https://api.github.com/repos/facebook/react",
  "labels_url": "https://api.github.com/repos/facebook/react/issues/5920/labels{/name}",
  "comments_url": "https://api.github.com/repos/facebook/react/issues/5920/comments",
  "events_url": "https://api.github.com/repos/facebook/react/issues/5920/events",
  "html_url": "https://github.com/facebook/react/issues/5920",
  "id": 128647321,
  "node_id": "MDU6SXNzdWUxMjg2NDczMjE=",
  "number": 5920,
  "title": "startWatchingForChangeEventIE8 getting called in Google Chrome",
  "user": {
    "login": "cdonohue",
    "id": 1928846,
    "node_id": "MDQ6VXNlcjE5Mjg4NDY=",
    "avatar_url": "https://avatars3.githubusercontent.com/u/1928846?v=4",
    "gravatar_id": "",
    "url": "https://api.github.com/users/cdonohue",
    "html_url": "https://github.com/cdonohue",
    "followers_url": "https://api.github.com/users/cdonohue/followers",
    "following_url": "https://api.github.com/users/cdonohue/following{/other_user}",
    "gists_url": "https://api.github.com/users/cdonohue/gists{/gist_id}",
    "starred_url": "https://api.github.com/users/cdonohue/starred{/owner}{/repo}",
    "subscriptions_url": "https://api.github.com/users/cdonohue/subscriptions",
    "organizations_url": "https://api.github.com/users/cdonohue/orgs",
    "repos_url": "https://api.github.com/users/cdonohue/repos",
    "events_url": "https://api.github.com/users/cdonohue/events{/privacy}",
    "received_events_url": "https://api.github.com/users/cdonohue/received_events",
    "type": "User",
    "site_admin": false
  },
  "labels": [
    {
      "id": 155984160,
      "node_id": "MDU6TGFiZWwxNTU5ODQxNjA=",
      "url": "https://api.github.com/repos/facebook/react/labels/Status:%20Unconfirmed",
      "name": "Status: Unconfirmed",
      "color": "d4c5f9",
      "default": false
    }
  ],
  "state": "closed",
  "locked": false,
  "assignee": null,
  "assignees": [

  ],
  "milestone": null,
  "comments": 9,
  "created_at": "2016-01-25T21:44:11Z",
  "updated_at": "2016-02-07T17:54:03Z",
  "closed_at": "2016-02-07T17:54:03Z",
  "author_association": "NONE",
  "body": "I'm getting errors in the console when attempting to render `select` and `input` components.\n\n```\nUncaught TypeError: activeElement.attachEvent is not a function\n```\n\nand\n\n```\nUncaught TypeError: activeElement.detachEvent is not a function\n```\n\nThe errors get thrown from https://github.com/facebook/react/blob/master/src/renderers/dom/client/eventPlugins/ChangeEventPlugin.js#L103-L107 and https://github.com/facebook/react/blob/master/src/renderers/dom/client/eventPlugins/ChangeEventPlugin.js#L109-L116\n\nThese methods should only run in legacy IE browsers, correct?\n\nI am having this issue in Google Chrome 48.0.2564.82 (Mac). \n",
  "closed_by": {
    "login": "jimfb",
    "id": 9595985,
    "node_id": "MDQ6VXNlcjk1OTU5ODU=",
    "avatar_url": "https://avatars3.githubusercontent.com/u/9595985?v=4",
    "gravatar_id": "",
    "url": "https://api.github.com/users/jimfb",
    "html_url": "https://github.com/jimfb",
    "followers_url": "https://api.github.com/users/jimfb/followers",
    "following_url": "https://api.github.com/users/jimfb/following{/other_user}",
    "gists_url": "https://api.github.com/users/jimfb/gists{/gist_id}",
    "starred_url": "https://api.github.com/users/jimfb/starred{/owner}{/repo}",
    "subscriptions_url": "https://api.github.com/users/jimfb/subscriptions",
    "organizations_url": "https://api.github.com/users/jimfb/orgs",
    "repos_url": "https://api.github.com/users/jimfb/repos",
    "events_url": "https://api.github.com/users/jimfb/events{/privacy}",
    "received_events_url": "https://api.github.com/users/jimfb/received_events",
    "type": "User",
    "site_admin": false
  }
}
