{
  "url": "https://api.github.com/repos/facebook/react/issues/7924",
  "repository_url": "https://api.github.com/repos/facebook/react",
  "labels_url": "https://api.github.com/repos/facebook/react/issues/7924/labels{/name}",
  "comments_url": "https://api.github.com/repos/facebook/react/issues/7924/comments",
  "events_url": "https://api.github.com/repos/facebook/react/issues/7924/events",
  "html_url": "https://github.com/facebook/react/issues/7924",
  "id": 181950841,
  "node_id": "MDU6SXNzdWUxODE5NTA4NDE=",
  "number": 7924,
  "title": "dangerouslySetInnerHTML={someOfMyText} causes Chrome console(developer tool) to freeze.  No problem on firefox though",
  "user": {
    "login": "wickedrahul",
    "id": 17119296,
    "node_id": "MDQ6VXNlcjE3MTE5Mjk2",
    "avatar_url": "https://avatars3.githubusercontent.com/u/17119296?v=4",
    "gravatar_id": "",
    "url": "https://api.github.com/users/wickedrahul",
    "html_url": "https://github.com/wickedrahul",
    "followers_url": "https://api.github.com/users/wickedrahul/followers",
    "following_url": "https://api.github.com/users/wickedrahul/following{/other_user}",
    "gists_url": "https://api.github.com/users/wickedrahul/gists{/gist_id}",
    "starred_url": "https://api.github.com/users/wickedrahul/starred{/owner}{/repo}",
    "subscriptions_url": "https://api.github.com/users/wickedrahul/subscriptions",
    "organizations_url": "https://api.github.com/users/wickedrahul/orgs",
    "repos_url": "https://api.github.com/users/wickedrahul/repos",
    "events_url": "https://api.github.com/users/wickedrahul/events{/privacy}",
    "received_events_url": "https://api.github.com/users/wickedrahul/received_events",
    "type": "User",
    "site_admin": false
  },
  "labels": [
    {
      "id": 155984160,
      "node_id": "MDU6TGFiZWwxNTU5ODQxNjA=",
      "url": "https://api.github.com/repos/facebook/react/labels/Status:%20Unconfirmed",
      "name": "Status: Unconfirmed",
      "color": "d4c5f9",
      "default": false
    }
  ],
  "state": "closed",
  "locked": false,
  "assignee": null,
  "assignees": [

  ],
  "milestone": null,
  "comments": 2,
  "created_at": "2016-10-10T07:28:58Z",
  "updated_at": "2016-10-12T14:36:01Z",
  "closed_at": "2016-10-12T14:36:01Z",
  "author_association": "NONE",
  "body": "**Do you want to request a _feature_ or report a _bug_?**\n\n**What is the current behavior?**\n\n**If the current behavior is a bug, please provide the steps to reproduce and if possible a minimal demo of the problem via https://jsfiddle.net or similar (template: https://jsfiddle.net/reactjs/69z2wepo/).**\n\n**What is the expected behavior?**\n\n**Which versions of React, and which browser / OS are affected by this issue? Did this work in previous versions of React?**\n",
  "closed_by": {
    "login": "aweary",
    "id": 6886061,
    "node_id": "MDQ6VXNlcjY4ODYwNjE=",
    "avatar_url": "https://avatars2.githubusercontent.com/u/6886061?v=4",
    "gravatar_id": "",
    "url": "https://api.github.com/users/aweary",
    "html_url": "https://github.com/aweary",
    "followers_url": "https://api.github.com/users/aweary/followers",
    "following_url": "https://api.github.com/users/aweary/following{/other_user}",
    "gists_url": "https://api.github.com/users/aweary/gists{/gist_id}",
    "starred_url": "https://api.github.com/users/aweary/starred{/owner}{/repo}",
    "subscriptions_url": "https://api.github.com/users/aweary/subscriptions",
    "organizations_url": "https://api.github.com/users/aweary/orgs",
    "repos_url": "https://api.github.com/users/aweary/repos",
    "events_url": "https://api.github.com/users/aweary/events{/privacy}",
    "received_events_url": "https://api.github.com/users/aweary/received_events",
    "type": "User",
    "site_admin": false
  }
}
