{
  "url": "https://api.github.com/repos/facebook/react/issues/8382",
  "repository_url": "https://api.github.com/repos/facebook/react",
  "labels_url": "https://api.github.com/repos/facebook/react/issues/8382/labels{/name}",
  "comments_url": "https://api.github.com/repos/facebook/react/issues/8382/comments",
  "events_url": "https://api.github.com/repos/facebook/react/issues/8382/events",
  "html_url": "https://github.com/facebook/react/issues/8382",
  "id": 191078669,
  "node_id": "MDU6SXNzdWUxOTEwNzg2Njk=",
  "number": 8382,
  "title": "Documentation: missing mention to refs",
  "user": {
    "login": "sam-artuso",
    "id": 3853889,
    "node_id": "MDQ6VXNlcjM4NTM4ODk=",
    "avatar_url": "https://avatars1.githubusercontent.com/u/3853889?v=4",
    "gravatar_id": "",
    "url": "https://api.github.com/users/sam-artuso",
    "html_url": "https://github.com/sam-artuso",
    "followers_url": "https://api.github.com/users/sam-artuso/followers",
    "following_url": "https://api.github.com/users/sam-artuso/following{/other_user}",
    "gists_url": "https://api.github.com/users/sam-artuso/gists{/gist_id}",
    "starred_url": "https://api.github.com/users/sam-artuso/starred{/owner}{/repo}",
    "subscriptions_url": "https://api.github.com/users/sam-artuso/subscriptions",
    "organizations_url": "https://api.github.com/users/sam-artuso/orgs",
    "repos_url": "https://api.github.com/users/sam-artuso/repos",
    "events_url": "https://api.github.com/users/sam-artuso/events{/privacy}",
    "received_events_url": "https://api.github.com/users/sam-artuso/received_events",
    "type": "User",
    "site_admin": false
  },
  "labels": [

  ],
  "state": "closed",
  "locked": false,
  "assignee": {
    "login": "lacker",
    "id": 106475,
    "node_id": "MDQ6VXNlcjEwNjQ3NQ==",
    "avatar_url": "https://avatars1.githubusercontent.com/u/106475?v=4",
    "gravatar_id": "",
    "url": "https://api.github.com/users/lacker",
    "html_url": "https://github.com/lacker",
    "followers_url": "https://api.github.com/users/lacker/followers",
    "following_url": "https://api.github.com/users/lacker/following{/other_user}",
    "gists_url": "https://api.github.com/users/lacker/gists{/gist_id}",
    "starred_url": "https://api.github.com/users/lacker/starred{/owner}{/repo}",
    "subscriptions_url": "https://api.github.com/users/lacker/subscriptions",
    "organizations_url": "https://api.github.com/users/lacker/orgs",
    "repos_url": "https://api.github.com/users/lacker/repos",
    "events_url": "https://api.github.com/users/lacker/events{/privacy}",
    "received_events_url": "https://api.github.com/users/lacker/received_events",
    "type": "User",
    "site_admin": false
  },
  "assignees": [
    {
      "login": "lacker",
      "id": 106475,
      "node_id": "MDQ6VXNlcjEwNjQ3NQ==",
      "avatar_url": "https://avatars1.githubusercontent.com/u/106475?v=4",
      "gravatar_id": "",
      "url": "https://api.github.com/users/lacker",
      "html_url": "https://github.com/lacker",
      "followers_url": "https://api.github.com/users/lacker/followers",
      "following_url": "https://api.github.com/users/lacker/following{/other_user}",
      "gists_url": "https://api.github.com/users/lacker/gists{/gist_id}",
      "starred_url": "https://api.github.com/users/lacker/starred{/owner}{/repo}",
      "subscriptions_url": "https://api.github.com/users/lacker/subscriptions",
      "organizations_url": "https://api.github.com/users/lacker/orgs",
      "repos_url": "https://api.github.com/users/lacker/repos",
      "events_url": "https://api.github.com/users/lacker/events{/privacy}",
      "received_events_url": "https://api.github.com/users/lacker/received_events",
      "type": "User",
      "site_admin": false
    }
  ],
  "milestone": null,
  "comments": 4,
  "created_at": "2016-11-22T17:51:48Z",
  "updated_at": "2017-04-16T11:17:38Z",
  "closed_at": "2017-04-16T11:17:38Z",
  "author_association": "NONE",
  "body": "**Do you want to request a *feature* or report a *bug*?**\r\n\r\nA bug.\r\n\r\n**What is the current behavior?**\r\n\r\nThe [Thinking in React document](https://facebook.github.io/react/docs/thinking-in-react.html) in the Quickstart section of the documentation contains some code that uses refs but refs are not mentioned in the text.\r\n\r\nRefs are used in the JS code in [this pen](http://codepen.io/snakajima/pen/JbYQvL?editors=0010#0) at lines 71 and 78.\r\n\r\n**What is the expected behavior?**\r\n\r\nRefs should be explained in Thinking in React or in an earlier section of the Quickstart section of the documentation so that the reader is able to follow along.\r\n\r\n**Which versions of React, and which browser / OS are affected by this issue? Did this work in previous versions of React?**\r\n\r\nReact v15.4.0. The issue is live at [this URL](https://facebook.github.io/react/docs/thinking-in-react.html).",
  "closed_by": {
    "login": "gaearon",
    "id": 810438,
    "node_id": "MDQ6VXNlcjgxMDQzOA==",
    "avatar_url": "https://avatars0.githubusercontent.com/u/810438?v=4",
    "gravatar_id": "",
    "url": "https://api.github.com/users/gaearon",
    "html_url": "https://github.com/gaearon",
    "followers_url": "https://api.github.com/users/gaearon/followers",
    "following_url": "https://api.github.com/users/gaearon/following{/other_user}",
    "gists_url": "https://api.github.com/users/gaearon/gists{/gist_id}",
    "starred_url": "https://api.github.com/users/gaearon/starred{/owner}{/repo}",
    "subscriptions_url": "https://api.github.com/users/gaearon/subscriptions",
    "organizations_url": "https://api.github.com/users/gaearon/orgs",
    "repos_url": "https://api.github.com/users/gaearon/repos",
    "events_url": "https://api.github.com/users/gaearon/events{/privacy}",
    "received_events_url": "https://api.github.com/users/gaearon/received_events",
    "type": "User",
    "site_admin": false
  }
}
